hyclib/__init__.py
hyclib/io.py
hyclib/npf.py
hyclib/pd.py
hyclib/plot.py
hyclib/core/argparse.py
hyclib/core/clstools.py
hyclib/core/config.py
hyclib/core/configurable.py
hyclib/core/datetime.py
hyclib/core/exceptions.py
hyclib/core/functools.py
hyclib/core/itertools.py
hyclib/core/logging.py
hyclib/core/pprint.py
hyclib/core/random.py
hyclib/core/tempfile.py
hyclib/core/timeit.py
hyclib/core/warnings.py
hyclib/np/__init__.py
hyclib/np/core.py
hyclib/np/stats.py
hyclib/pt/__init__.py
hyclib/pt/core.py
hyclib/pt/integrate.py
hyclib/pt/stats.py
hyclib/sp/__init__.py
hyclib/sp/stats.py
hyclib-0.1.40.dist-info/LICENSE
hyclib-0.1.40.dist-info/METADATA
hyclib-0.1.40.dist-info/WHEEL
hyclib-0.1.40.dist-info/top_level.txt
hyclib-0.1.40.dist-info/RECORD
