Metadata-Version: 2.1
Name: hyclib
Version: 0.1.40
Summary: Commonly used tools across my own personal projects.
Author: Ho Yin Chau
License: MIT License
Project-URL: repository, https://github.com/hchau630/hyclib
Classifier: License :: OSI Approved :: MIT License
Classifier: Natural Language :: English
Classifier: Operating System :: OS Independent
Classifier: Programming Language :: Python :: 3.9
Requires-Python: >=3.9
License-File: LICENSE
Requires-Dist: tomli
Requires-Dist: platformdirs
Provides-Extra: data
Requires-Dist: numpy ; extra == 'data'
Requires-Dist: scipy ; extra == 'data'
Requires-Dist: torch >=2.1.0 ; extra == 'data'
Requires-Dist: statsmodels ; extra == 'data'
Requires-Dist: pandas ; extra == 'data'
Requires-Dist: tables ; extra == 'data'
Requires-Dist: h5py ; extra == 'data'
Requires-Dist: mat73 ; extra == 'data'
Requires-Dist: tqdm ; extra == 'data'
Provides-Extra: ml
Requires-Dist: numpy ; extra == 'ml'
Requires-Dist: scipy ; extra == 'ml'
Requires-Dist: torch >=2.1.0 ; extra == 'ml'
Requires-Dist: statsmodels ; extra == 'ml'
Provides-Extra: numerics
Requires-Dist: numpy ; extra == 'numerics'
Requires-Dist: scipy ; extra == 'numerics'
Requires-Dist: statsmodels ; extra == 'numerics'
Provides-Extra: viz
Requires-Dist: numpy ; extra == 'viz'
Requires-Dist: matplotlib ; extra == 'viz'
Requires-Dist: statsmodels ; extra == 'viz'
